{
  "buildTime": "2026-06-27T09:09:54.872Z",
  "commit": "de74bf6",
  "environment": "development",
  "feature": "monthly-close-v2-phase-1",
  "bundle": "index-DFEcZ5eB.js",
  "detectedClientAssets": [
    "index-DFEcZ5eB.js",
    "AppInvoices-DuWsdp3N.js",
    "AppMyProfile-CFirPH41.js",
    "AppEmployeeDetail-DLhLJA0a.js",
    "AppMyClosing-WyYRTYQj.js",
    "AppRates-HBSs8nEI.js",
    "AppDashboard-DJ2TekwW.js",
    "AppClosings-2hahN8eQ.js",
    "AppMonthlyCloseV2-D7lItgy0.js",
    "AppAttendance-DziLuPQP.js",
    "AppEmployees-DB-c6WJq.js",
    "AppProjects-Kydj90Qb.js",
    "AppReceivables-D6CImx_l.js",
    "AppWorkerInvoiceV2-B2VjU6Xw.js",
    "AppCompany-CFCiwaUa.js",
    "AppPasswordResets-BcF2Z9J-.js",
    "AppSupport-B440YG7r.js",
    "AppInvitations-788_I218.js",
    "AppPayments-BOacT3EF.js",
    "select-D2sIsAvj.js",
    "format-Bv79THRM.js",
    "AppAuditLogs-Du7jW6qD.js",
    "attendanceStatus-DAwQqUMx.js",
    "AppConfirmationPdf-nZz-ucWL.js",
    "AppResetPassword-BfFZ1Cd8.js",
    "tabs-CATwhFTh.js",
    "index-DLRo8Aze.js",
    "table-Bd1Roq3g.js",
    "badge-0FHRMd6H.js",
    "index-DFB_0DyQ.js",
    "textarea-DQd-K1s0.js",
    "sun-BGDhlful.js",
    "landmark-CN6lE_yZ.js",
    "trash-2-BFrtkkfJ.js",
    "save-Cjux7fl8.js",
    "refresh-cw-DVewvvMf.js",
    "shield-check-DGYvlXiW.js",
    "file-down-CG7XqLr7.js",
    "receipt-Cp3NUDnj.js",
    "send-BNE_na_3.js",
    "pencil-VYNHkLrd.js",
    "startOfMonth-Ogd_8_G2.js",
    "download-kxyj8O3P.js",
    "calendar-MVtsffUH.js",
    "upload-DQ63Q-uM.js",
    "link-jYXmKTqP.js",
    "banknote-CLxPm87Y.js",
    "heart-Bn5Bm8cQ.js",
    "copy-D7KWAJRN.js",
    "lock-open-Mwls1gC_.js",
    "undo-2-BEjN5olj.js",
    "circle-x-DseM4a7K.js",
    "circle-check-Bf4MIWpF.js",
    "search-DIeCodyA.js",
    "chevron-right-CGm8Fu5N.js"
  ],
  "detectionNote": "Detected the largest hashed index-*.js client entry bundle from dist/public/assets after Vite build."
}
